{
  "defaults": {
    "n_plus": 7,
    "s_plus": 10,
    "v_plus": 5,
    "lipogram_letter": "e",
    "univocal_vowel": "e",
    "tautogram_letter": "a",
    "compliance_full": 1.0,
    "compliance_none": 0.0,
    "syllable_min": 1,
    "vowels": ["a", "e", "i", "o", "u"]
  },
  "limits": {
    "n_plus_replacements": 20,
    "s_plus_replacements": 20,
    "v_plus_replacements": 20,
    "word_lengths": 15,
    "pi_digits_preview": 15,
    "end_words": 6,
    "knight_preview_chars": 100
  },
  "rounding": {
    "css": 4,
    "compliance": 3,
    "difficulty": 6
  },
  "math": {
    "ratio_min": 1e-9,
    "log_base": 2
  },
  "snowball": {
    "generated_lines": 10,
    "min_length": 1,
    "max_length": 20,
    "length_tolerance": 1
  },
  "pilish": {
    "generated_lines": 10,
    "pi_note": "Word lengths match digits of π (3.141592653...)"
  },
  "fibonacci": {
    "fallback_sequence": [1, 1, 2, 3, 5, 8],
    "syllable_min": 1
  },
  "forms": {
    "sestina_lines": 39,
    "sestina_stanza_size": 6,
    "sestina_stanzas": 6,
    "sestina_envoi_lines": 3,
    "villanelle_lines": 19,
    "haiku_lines": 3,
    "limerick_lines": 5,
    "sonnet_lines": 14
  },
  "constraint_counts": {
    "line_count": 1,
    "rhyme_scheme": 1,
    "limerick_total": 2,
    "sonnet_line": 1,
    "sonnet_rhyme": 1,
    "villanelle_line": 1,
    "haiku_line": 1
  },
  "sonnet": {
    "schemes": ["ABABCDCDEFEFGG", "ABBAABBACDECDE"]
  },
  "meter": {
    "iambic_unit": ["da", "DUM"],
    "iambic_feet": 5
  },
  "villanelle": {
    "a1_positions": [0, 5, 11, 17],
    "a2_positions": [2, 8, 14, 18],
    "a_lines": [0, 2, 5, 8, 11, 14, 17, 18],
    "b_lines": [1, 3, 4, 6, 7, 9, 10, 12, 13, 15, 16]
  },
  "sestina": {
    "patterns": {
      "1": [6, 1, 5, 2, 4, 3],
      "2": [3, 6, 4, 1, 2, 5],
      "3": [5, 3, 2, 6, 1, 4],
      "4": [4, 5, 1, 3, 6, 2],
      "5": [2, 4, 6, 5, 3, 1]
    },
    "base_pattern": [0, 1, 2, 3, 4, 5],
    "envoi_pairs": [[2, 4], [6, 5], [3, 1]]
  },
  "haiku": {
    "syllable_targets": [5, 7, 5]
  },
  "knights_tour": {
    "moves": [[2, 1], [2, -1], [-2, 1], [-2, -1], [1, 2], [1, -2], [-1, 2], [-1, -2]]
  },
  "templates": {
    "sestina_description": "Sestina: 39 lines, 6 stanzas of 6 lines + 3-line envoi, with rotating end-word pattern",
    "knight_description": "Knight's Tour: Text read following chess knight's L-shaped moves (2+1 squares)",
    "pilish_note": "Word lengths match digits of π (3.141592653...)",
    "snowball_note": "Each word is one letter longer than the previous",
    "lipogram_note": "Written without using the letter '{letter}'",
    "univocal_note": "All words contain only the vowel '{vowel}'",
    "fibonacci_note": "Syllables per line follow Fibonacci sequence: 1, 1, 2, 3, 5, 8",
    "pantoum_analysis": "Pantoum requires detailed cross-stanza repetition tracking",
    "grid_dimensions_empty": "0x0",
    "vowel_error": "Vowel must be one of: {vowels}"
  }
}
